{"cameraMode":{"drawMode":0,"name":"Shaded","section":"Shading Mode"},"sceneLighting":true,"audioPlay":false,"sceneViewState":{"m_AlwaysRefresh":false,"showFog":true,"showSkybox":true,"showFlares":true,"showImageEffects":true,"showParticleSystems":true,"showVisualEffectGraphs":true,"m_FxEnabled":true},"in2DMode":false,"pivot":{"x":-5.180180072784424,"y":-1.5501426458358765,"z":10.035256385803223},"rotation":{"x":-0.1784752756357193,"y":0.1577666848897934,"z":-0.02900277078151703,"w":-0.9708240628242493},"size":8.317895889282227,"orthographic":false}